<?xml version="1.0"?>
<opencv_storage>
<stage21>
  <maxWeakCount>20</maxWeakCount>
  <stageThreshold>-6.3535660505294800e-01</stageThreshold>
  <weakClassifiers>
    <_>
      <internalNodes>
        0 -1 1067 721330786 -2122398330 -1494241522 107914986 1961797280
        1733619015 1245553934 40414930</internalNodes>
      <leafValues>
        1.1570247821509838e-02 6.3011455535888672e-01</leafValues></_>
    <_>
      <internalNodes>
        0 -1 582 1560654225 144220688 1393641855 747440215 -1765179373
        831569935 711568076 1057304486</internalNodes>
      <leafValues>
        -3.1826081871986389e-01 3.2579123973846436e-01</leafValues></_>
    <_>
      <internalNodes>
        0 -1 533 -663359228 379689571 -2130079394 1422917705 -2003648329
        -1977040760 -1635776328 992774347</internalNodes>
      <leafValues>
        -5.8290481567382812e-01 1.6771472990512848e-01</leafValues></_>
    <_>
      <internalNodes>
        0 -1 933 -527794108 -767245975 -1064516899 1674430533 193515744
        -682573672 2027784394 286794587</internalNodes>
      <leafValues>
        -4.0802565217018127e-01 2.3839215934276581e-01</leafValues></_>
    <_>
      <internalNodes>
        0 -1 155 1511583731 1647791179 1072623573 -144737537 -1200444270
        -32106198 -1753415748 -10752422</internalNodes>
      <leafValues>
        -1.6020597517490387e-01 5.5379670858383179e-01</leafValues></_>
    <_>
      <internalNodes>
        0 -1 80 -468404740 -1910718332 210218868 -1049288613 974128559
        1313620096 537545028 -490371000</internalNodes>
      <leafValues>
        -5.7543122768402100e-01 1.3967107236385345e-01</leafValues></_>
    <_>
      <internalNodes>
        0 -1 1044 432085897 599698225 587185847 -56562848 -1544315229
        -2017666372 389274363 -69484641</internalNodes>
      <leafValues>
        -1.8058830499649048e-01 5.5928874015808105e-01</leafValues></_>
    <_>
      <internalNodes>
        0 -1 331 1758529312 1490420249 608275602 2129678985 -805093148
        -525840349 2028572881 457261217</internalNodes>
      <leafValues>
        -4.2610460519790649e-01 2.2547779977321625e-01</leafValues></_>
    <_>
      <internalNodes>
        0 -1 909 -275195179 -1144193002 1375694353 -1050325379 -18942071
        -1146175561 -1141532683 -1156620441</internalNodes>
      <leafValues>
        -1.8828506767749786e-01 4.8442670702934265e-01</leafValues></_>
    <_>
      <internalNodes>
        0 -1 1057 713688580 243865808 1141185602 365697490 -930609408
        -2073526265 -120780158 53129537</internalNodes>
      <leafValues>
        -5.0171834230422974e-01 1.7996440827846527e-01</leafValues></_>
    <_>
      <internalNodes>
        0 -1 986 -1031022353 -1881583944 -59117889 -1512608341
        -1729771104 1421115356 -349376319 722647380</internalNodes>
      <leafValues>
        -2.3119497299194336e-01 3.7474310398101807e-01</leafValues></_>
    <_>
      <internalNodes>
        0 -1 1056 1703487508 -2034660202 -1005923416 1558071550
        728335442 -573046774 -1253280317 -1143604152</internalNodes>
      <leafValues>
        -2.9369083046913147e-01 2.8053957223892212e-01</leafValues></_>
    <_>
      <internalNodes>
        0 -1 710 -267742349 -572919111 2103449629 -612395651 -286066445
        -58552060 302094067 -1419176804</internalNodes>
      <leafValues>
        -1.4015825092792511e-01 5.8280599117279053e-01</leafValues></_>
    <_>
      <internalNodes>
        0 -1 321 -77335597 -550934470 -3667625 -334448410 -624500335
        -160133448 -1009000065 -580921685</internalNodes>
      <leafValues>
        -1.2275650352239609e-01 6.4365953207015991e-01</leafValues></_>
    <_>
      <internalNodes>
        0 -1 290 552986824 -1198329921 -1438783779 -738568547 402096334
        1600683615 -1092617432 -684076354</internalNodes>
      <leafValues>
        -2.6500028371810913e-01 3.2871833443641663e-01</leafValues></_>
    <_>
      <internalNodes>
        0 -1 1196 2070117515 -882023227 -1636298368 1474595949
        -820779814 400887166 906040199 -607398821</internalNodes>
      <leafValues>
        -1.7885962128639221e-01 4.7875693440437317e-01</leafValues></_>
    <_>
      <internalNodes>
        0 -1 863 -689274250 2006960796 -1073702702 293637173 -2139059247
        310937730 -1442297367 461408259</internalNodes>
      <leafValues>
        -3.6889979243278503e-01 2.4682645499706268e-01</leafValues></_>
    <_>
      <internalNodes>
        0 -1 102 1745851338 -776795981 1926998564 1639507922 -507551841
        1264512878 -212395783 -170021174</internalNodes>
      <leafValues>
        -1.9998553395271301e-01 4.3541985750198364e-01</leafValues></_>
    <_>
      <internalNodes>
        0 -1 6 118133357 541239698 1257995 979124416 -1944527034
        1753761952 1929415651 -1962389193</internalNodes>
      <leafValues>
        -3.2839801907539368e-01 2.7512887120246887e-01</leafValues></_>
    <_>
      <internalNodes>
        0 -1 626 -493296720 -130022101 -1720933711 1445822009 -985877087
        -1085509665 585553395 -1441704527</internalNodes>
      <leafValues>
        -2.4629178643226624e-01 3.6321261525154114e-01</leafValues></_></weakClassifiers></stage21>
</opencv_storage>
